qp/__init__.py
qp/_version.py
qp/plotting.py
qp/version.py
qp/core/__init__.py
qp/core/ensemble.py
qp/core/factory.py
qp/core/lazy_modules.py
qp/metrics/__init__.py
qp/metrics/array_metrics.py
qp/metrics/base_metric_classes.py
qp/metrics/brier.py
qp/metrics/concrete_metric_classes.py
qp/metrics/factory.py
qp/metrics/goodness_of_fit.py
qp/metrics/lazy_modules.py
qp/metrics/metrics.py
qp/metrics/parallel_metrics.ipynb
qp/metrics/pit.py
qp/metrics/point_estimate_metric_classes.py
qp/metrics/util_funcs.py
qp/parameterizations/__init__.py
qp/parameterizations/base.py
qp/parameterizations/hist/__init__.py
qp/parameterizations/hist/hist.py
qp/parameterizations/hist/hist_utils.py
qp/parameterizations/interp/__init__.py
qp/parameterizations/interp/interp.py
qp/parameterizations/interp/interp_utils.py
qp/parameterizations/mixmod/__init__.py
qp/parameterizations/mixmod/mixmod.py
qp/parameterizations/mixmod/mixmod_utils.py
qp/parameterizations/packed_interp/__init__.py
qp/parameterizations/packed_interp/packed_interp.py
qp/parameterizations/packed_interp/packing_utils.py
qp/parameterizations/quant/__init__.py
qp/parameterizations/quant/abstract_pdf_constructor.py
qp/parameterizations/quant/cdf_spline_derivative.py
qp/parameterizations/quant/dual_spline_average.py
qp/parameterizations/quant/piecewise_constant.py
qp/parameterizations/quant/piecewise_linear.py
qp/parameterizations/quant/quant.py
qp/parameterizations/quant/quant_utils.py
qp/parameterizations/sparse_interp/__init__.py
qp/parameterizations/sparse_interp/sparse.py
qp/parameterizations/sparse_interp/sparse_rep.py
qp/parameterizations/sparse_interp/sparse_utils.py
qp/parameterizations/spline/__init__.py
qp/parameterizations/spline/spline.py
qp/parameterizations/spline/spline_utils.py
qp/utils/__init__.py
qp/utils/array.py
qp/utils/conversion.py
qp/utils/dictionary.py
qp/utils/interpolation.py
qp_prob-1.0.2.dist-info/licenses/LICENSE
qp_prob-1.0.2.dist-info/METADATA
qp_prob-1.0.2.dist-info/WHEEL
qp_prob-1.0.2.dist-info/top_level.txt
qp_prob-1.0.2.dist-info/RECORD
