Metadata-Version: 2.4
Name: qp-prob
Version: 1.0.2
Author-email: "LSST Dark Energy Science Collaboration (DESC)" <later@later.com>
License: MIT License
Classifier: Development Status :: 4 - Beta
Classifier: License :: OSI Approved :: MIT License
Classifier: Intended Audience :: Developers
Classifier: Intended Audience :: Science/Research
Classifier: Operating System :: OS Independent
Classifier: Programming Language :: Python
Requires-Python: >=3.10
License-File: LICENSE
Requires-Dist: numpy>=2.0
Requires-Dist: scipy>=1.13
Requires-Dist: tables-io>=1.0.0
Requires-Dist: deprecated
Provides-Extra: full
Requires-Dist: tables-io[full]; extra == "full"
Requires-Dist: matplotlib; extra == "full"
Requires-Dist: pytdigest; extra == "full"
Requires-Dist: scikit-learn>=1.0; extra == "full"
Provides-Extra: dev
Requires-Dist: tables-io[full]; extra == "dev"
Requires-Dist: matplotlib; extra == "dev"
Requires-Dist: scikit-learn>=1.0; extra == "dev"
Requires-Dist: pytest; extra == "dev"
Requires-Dist: pytest-cov; extra == "dev"
Requires-Dist: pre-commit; extra == "dev"
Requires-Dist: pylint; extra == "dev"
Requires-Dist: packaging; extra == "dev"
Requires-Dist: pillow; extra == "dev"
Requires-Dist: cycler; extra == "dev"
Requires-Dist: pytdigest; extra == "dev"
Requires-Dist: python-dateutil; extra == "dev"
Requires-Dist: kiwisolver; extra == "dev"
Requires-Dist: joblib; extra == "dev"
Requires-Dist: threadpoolctl; extra == "dev"
Requires-Dist: pylint; extra == "dev"
Requires-Dist: mpi4py; extra == "dev"
Requires-Dist: coverage; extra == "dev"
Requires-Dist: ipyparallel; extra == "dev"
Provides-Extra: docs
Requires-Dist: nbsphinx; extra == "docs"
Requires-Dist: sphinx>6.3.1; extra == "docs"
Requires-Dist: sphinx_rtd_theme; extra == "docs"
Requires-Dist: sphinx-autoapi; extra == "docs"
Requires-Dist: sphinx_design; extra == "docs"
Requires-Dist: myst-nb; extra == "docs"
Requires-Dist: myst-parser>=4; extra == "docs"
Requires-Dist: sphinx-copybutton; extra == "docs"
Requires-Dist: numpydoc; extra == "docs"
Dynamic: license-file
